setup.py
formtags/__init__.py
formtags/html.py
formtags/schema.py
formtags/util.py
formtags.egg-info/PKG-INFO
formtags.egg-info/SOURCES.txt
formtags.egg-info/dependency_links.txt
formtags.egg-info/entry_points.txt
formtags.egg-info/not-zip-safe
formtags.egg-info/top_level.txt