Metadata-Version: 1.0
Name: formtags
Version: 0.4.1
Summary: python library to generate forms and validate them using formencode and sqlalchemy
Home-page: http://code.google.com/p/py-formtags/
Author: Michael van Tellingen
Author-email: michaelvantellingen@gmail.com
License: UNKNOWN
Platform: UNKNOWN
